pytest_iam/__init__.py
pytest_iam-0.2.4.dist-info/METADATA
pytest_iam-0.2.4.dist-info/WHEEL
pytest_iam-0.2.4.dist-info/entry_points.txt
pytest_iam-0.2.4.dist-info/licenses/LICENSE.md
pytest_iam-0.2.4.dist-info/RECORD
