Metadata-Version: 2.4
Name: pytest-iam
Version: 0.2.4
Summary: A fully functional OAUTH2 / OpenID Connect (OIDC) / SCIM server to be used in your testsuite
Author-email: Yaal Coop <contact@yaal.coop>
License-Expression: MIT
License-File: LICENSE.md
Keywords: iam,identity,oauth,oauth2,oidc,openid,pytest,scim,unit tests
Classifier: Development Status :: 4 - Beta
Classifier: Environment :: Web Environment
Classifier: Framework :: Pytest
Classifier: Intended Audience :: Developers
Classifier: License :: OSI Approved :: MIT License
Classifier: Operating System :: OS Independent
Classifier: Programming Language :: Python
Classifier: Programming Language :: Python :: 3.9
Classifier: Programming Language :: Python :: 3.10
Classifier: Programming Language :: Python :: 3.11
Classifier: Programming Language :: Python :: 3.12
Classifier: Programming Language :: Python :: Implementation :: CPython
Requires-Python: >=3.10
Requires-Dist: canaille[oidc]>=0.0.78
Requires-Dist: faker>=21.0.0
Requires-Dist: portpicker>=1.6.0
Requires-Dist: pytest>=7.0.0
